TrueRandomness/__init__.py
TrueRandomness/randomness.py
TrueRandomness-1.2.dist-info/METADATA
TrueRandomness-1.2.dist-info/WHEEL
TrueRandomness-1.2.dist-info/top_level.txt
TrueRandomness-1.2.dist-info/RECORD
