Metadata-Version: 2.1
Name: TrueRandomness
Version: 1.2
Summary: A Python library that generates true randomness using real-time data.
Home-page: https://github.com/SForces/TrueRandomness-Python
Author: SForces
Author-email: forces3564@gmail.com
Classifier: Programming Language :: Python :: 3
Classifier: License :: OSI Approved :: MIT License
Classifier: Operating System :: OS Independent
Requires-Python: >=3.6
